gumiyabot-1.1.3.dist-info/METADATA
gumiyabot-1.1.3.dist-info/WHEEL
gumiyabot-1.1.3.dist-info/entry_points.txt
gumiyabot-1.1.3.dist-info/licenses/LICENSE
gumiyabot/__init__.py
gumiyabot/__main__.py
gumiyabot/bancho.py
gumiyabot/twitch.py
gumiyabot/utils.py
gumiyabot-1.1.3.dist-info/RECORD
