Metadata-Version: 2.1
Name: gumiyabot
Version: 1.1.3
Summary: Standalone Twitch + Bancho IRC bot for handling osu! beatmap requests
Keywords: osu twitch gumiya
Author-Email: Peter Rowlands <peter@pmrowla.com>
License: MIT
Classifier: Development Status :: 5 - Production/Stable
Classifier: Framework :: AsyncIO
Classifier: Intended Audience :: Developers
Classifier: License :: OSI Approved :: MIT License
Classifier: Programming Language :: Python :: 3.11
Classifier: Programming Language :: Python :: 3.12
Classifier: Programming Language :: Python :: 3.13
Classifier: Programming Language :: Python :: 3.14
Classifier: Topic :: Communications :: Chat :: Internet Relay Chat
Classifier: Topic :: Games/Entertainment
Project-URL: Homepage, https://github.com/pmrowla/gumiyabot
Requires-Python: >=3.11
Requires-Dist: aiohttp>=2.0.0
Requires-Dist: irc3>=1.0.0
Requires-Dist: ossapi[async]>=5.3.0
